{
    "parent": "block/block",
    "textures": {
        "particle": "#horizontal"
    },
    "elements": [
        {
            "from": [ 0, 8, 0 ],
            "to": [ 16, 16, 16 ],
            "faces": {
                "down":  { "uv": [ 0, 0, 16, 16 ], "texture": "#full" },
                "up":    { "uv": [ 0, 0, 16, 16 ], "texture": "#full", "cullface": "up" },
                "north": { "uv": [ 0, 0, 16,  8 ], "texture": "#horizontal", "cullface": "north" },
                "south": { "uv": [ 0, 0, 16,  8 ], "texture": "#horizontal", "cullface": "south" },
                "west":  { "uv": [ 0, 0, 16,  8 ], "texture": "#horizontal", "cullface": "west" },
                "east":  { "uv": [ 0, 0, 16,  8 ], "texture": "#horizontal", "cullface": "east" }
            }
        }
    ]
}